tecoradors/__init__.py
tecoradors/tecoradors.py
tecoradors_elunico-8.3.1.dist-info/licenses/LICENSE
tecoradors_elunico-8.3.1.dist-info/METADATA
tecoradors_elunico-8.3.1.dist-info/WHEEL
tecoradors_elunico-8.3.1.dist-info/top_level.txt
tecoradors_elunico-8.3.1.dist-info/RECORD
