Metadata-Version: 2.4
Name: tecoradors-elunico
Version: 8.3.1
Summary: A small collection of decorators I like to use often
Home-page: https://github.com/elunico/tecoradors
Author: Thomas Povinelli
Author-email: tompov227@gmail.com
Classifier: Programming Language :: Python :: 3
Classifier: License :: OSI Approved :: MIT License
Classifier: Operating System :: OS Independent
Requires-Python: >=3.10
License-File: LICENSE
Dynamic: author
Dynamic: author-email
Dynamic: classifier
Dynamic: description
Dynamic: description-content-type
Dynamic: home-page
Dynamic: license-file
Dynamic: requires-python
Dynamic: summary
